reportermate/__init__.py
reportermate/command_line.py
reportermate/reportermate.py
reportermate-0.5.2.dist-info/LICENCE.txt
reportermate-0.5.2.dist-info/METADATA
reportermate-0.5.2.dist-info/WHEEL
reportermate-0.5.2.dist-info/entry_points.txt
reportermate-0.5.2.dist-info/top_level.txt
reportermate-0.5.2.dist-info/RECORD
