Metadata-Version: 2.1
Name: reportermate
Version: 0.5.2
Summary: Automated news stories and reports from datasets
Home-page: http://reportermate.com/
Author: Nick Evershed
Author-email: nick.evershed@gmail.com
License: MIT
Keywords: data-analysis text data analysis
Platform: UNKNOWN
Classifier: Development Status :: 1 - Planning
Classifier: License :: OSI Approved :: MIT License
Classifier: Programming Language :: Python :: 2.7
Classifier: Topic :: Scientific/Engineering :: Information Analysis
Requires-Dist: pandas
Requires-Dist: pybars3
Requires-Dist: messytables
Requires-Dist: pydateinfer
Requires-Dist: simplejson
Requires-Dist: tableschema
